MultiInstanceLinux/init.py
MultiInstanceLinux/multi_instance.py
MultiInstanceLinux/script_setup.py
MultiInstanceLinux/config/default_config.py
MultiInstanceLinux/helper_modules/logging.py
MultiInstanceLinux-1.3.5.dist-info/LICENSE
MultiInstanceLinux-1.3.5.dist-info/METADATA
MultiInstanceLinux-1.3.5.dist-info/WHEEL
MultiInstanceLinux-1.3.5.dist-info/entry_points.txt
MultiInstanceLinux-1.3.5.dist-info/top_level.txt
MultiInstanceLinux-1.3.5.dist-info/RECORD
