Metadata-Version: 2.1
Name: MultiInstanceLinux
Version: 1.3.5
Summary: Multi Instance Macro Handler for Minecraft on Linux.
Home-page: https://github.com/sathya-pramodh/MultiInstanceLinux
Author: sathya-pramodh
Author-email: sathyapramodh17@gmail.com
Project-URL: Bug Tracker, https://github.com/sathya-pramodh/MultiInstanceLinux/issues
Classifier: Programming Language :: Python :: 3
Classifier: License :: OSI Approved :: MIT License
Requires-Python: >=3.7
License-File: LICENSE
Requires-Dist: keyboard
Requires-Dist: obs-websocket-py
